torchvis/__init__.py
torchvis/selfish.py
torchvis/selflib/util.py
torchvis/stftlib.py
torchvis-0.4.0.dist-info/WHEEL
torchvis-0.4.0.dist-info/METADATA
torchvis-0.4.0.dist-info/RECORD
