Metadata-Version: 2.1
Name: torchvis
Version: 0.4.0
Summary: Pytorch visualization experiments
License: MIT
Author: Shawn Presser
Requires-Python: >=3.6,<4.0
Classifier: License :: OSI Approved :: MIT License
Classifier: Programming Language :: Python :: 3
Classifier: Programming Language :: Python :: 3.6
Classifier: Programming Language :: Python :: 3.7
Classifier: Programming Language :: Python :: 3.8
Classifier: Programming Language :: Python :: 3.9
Requires-Dist: ansi-escapes (>=0.1.1,<0.2.0)
Requires-Dist: ansi-styles (>=0.2.2,<0.3.0)
Requires-Dist: supports-color (>=0.1.2,<0.2.0)
